{"nodes": [{"id": "index", "label": "index.ts", "file_type": "code", "source_file": "lib/store/index.ts", "source_location": "L1"}], "edges": [{"source": "index", "target": "zustand", "relation": "imports_from", "confidence": "EXTRACTED", "source_file": "lib/store/index.ts", "source_location": "L3", "weight": 1.0}, {"source": "index", "target": "middleware", "relation": "imports_from", "confidence": "EXTRACTED", "source_file": "lib/store/index.ts", "source_location": "L4", "weight": 1.0}, {"source": "index", "target": "types", "relation": "imports_from", "confidence": "EXTRACTED", "source_file": "lib/store/index.ts", "source_location": "L5", "weight": 1.0}, {"source": "index", "target": "provider_registry", "relation": "imports_from", "confidence": "EXTRACTED", "source_file": "lib/store/index.ts", "source_location": "L6", "weight": 1.0}, {"source": "index", "target": "provider_registry", "relation": "imports_from", "confidence": "EXTRACTED", "source_file": "lib/store/index.ts", "source_location": "L7", "weight": 1.0}, {"source": "index", "target": "grid", "relation": "imports_from", "confidence": "EXTRACTED", "source_file": "lib/store/index.ts", "source_location": "L8", "weight": 1.0}, {"source": "index", "target": "types", "relation": "imports_from", "confidence": "EXTRACTED", "source_file": "lib/store/index.ts", "source_location": "L9", "weight": 1.0}, {"source": "index", "target": "model_config", "relation": "imports_from", "confidence": "EXTRACTED", "source_file": "lib/store/index.ts", "source_location": "L10", "weight": 1.0}, {"source": "index", "target": "agent_config", "relation": "imports_from", "confidence": "EXTRACTED", "source_file": "lib/store/index.ts", "source_location": "L11", "weight": 1.0}, {"source": "index", "target": "permissions", "relation": "imports_from", "confidence": "EXTRACTED", "source_file": "lib/store/index.ts", "source_location": "L12", "weight": 1.0}, {"source": "index", "target": "layers_tab_header", "relation": "imports_from", "confidence": "EXTRACTED", "source_file": "lib/store/index.ts", "source_location": "L13", "weight": 1.0}, {"source": "index", "target": "types", "relation": "imports_from", "confidence": "EXTRACTED", "source_file": "lib/store/index.ts", "source_location": "L15", "weight": 1.0}, {"source": "index", "target": "helpers", "relation": "imports_from", "confidence": "EXTRACTED", "source_file": "lib/store/index.ts", "source_location": "L16", "weight": 1.0}, {"source": "index", "target": "undo_actions", "relation": "imports_from", "confidence": "EXTRACTED", "source_file": "lib/store/index.ts", "source_location": "L18", "weight": 1.0}, {"source": "index", "target": "scene_actions", "relation": "imports_from", "confidence": "EXTRACTED", "source_file": "lib/store/index.ts", "source_location": "L19", "weight": 1.0}, {"source": "index", "target": "generation_actions", "relation": "imports_from", "confidence": "EXTRACTED", "source_file": "lib/store/index.ts", "source_location": "L20", "weight": 1.0}, {"source": "index", "target": "project_actions", "relation": "imports_from", "confidence": "EXTRACTED", "source_file": "lib/store/index.ts", "source_location": "L21", "weight": 1.0}, {"source": "index", "target": "agent_actions", "relation": "imports_from", "confidence": "EXTRACTED", "source_file": "lib/store/index.ts", "source_location": "L22", "weight": 1.0}, {"source": "index", "target": "timeline_actions", "relation": "imports_from", "confidence": "EXTRACTED", "source_file": "lib/store/index.ts", "source_location": "L23", "weight": 1.0}, {"source": "index", "target": "audio_actions", "relation": "imports_from", "confidence": "EXTRACTED", "source_file": "lib/store/index.ts", "source_location": "L24", "weight": 1.0}, {"source": "index", "target": "export_actions", "relation": "imports_from", "confidence": "EXTRACTED", "source_file": "lib/store/index.ts", "source_location": "L25", "weight": 1.0}, {"source": "index", "target": "inspector_actions", "relation": "imports_from", "confidence": "EXTRACTED", "source_file": "lib/store/index.ts", "source_location": "L26", "weight": 1.0}, {"source": "index", "target": "dev_actions", "relation": "imports_from", "confidence": "EXTRACTED", "source_file": "lib/store/index.ts", "source_location": "L27", "weight": 1.0}]}