{"nodes": [{"id": "dev_actions", "label": "dev-actions.ts", "file_type": "code", "source_file": "lib/store/dev-actions.ts", "source_location": "L1"}, {"id": "dev_actions_createdevactions", "label": "createDevActions()", "file_type": "code", "source_file": "lib/store/dev-actions.ts", "source_location": "L23"}], "edges": [{"source": "dev_actions", "target": "uuid", "relation": "imports_from", "confidence": "EXTRACTED", "source_file": "lib/store/dev-actions.ts", "source_location": "L3", "weight": 1.0}, {"source": "dev_actions", "target": "types", "relation": "imports_from", "confidence": "EXTRACTED", "source_file": "lib/store/dev-actions.ts", "source_location": "L4", "weight": 1.0}, {"source": "dev_actions", "target": "scenetemplate", "relation": "imports_from", "confidence": "EXTRACTED", "source_file": "lib/store/dev-actions.ts", "source_location": "L5", "weight": 1.0}, {"source": "dev_actions", "target": "testscenes", "relation": "imports_from", "confidence": "EXTRACTED", "source_file": "lib/store/dev-actions.ts", "source_location": "L6", "weight": 1.0}, {"source": "dev_actions", "target": "capabilityshowcasescenes", "relation": "imports_from", "confidence": "EXTRACTED", "source_file": "lib/store/dev-actions.ts", "source_location": "L16", "weight": 1.0}, {"source": "dev_actions", "target": "threeenvironmentshowcasescenes", "relation": "imports_from", "confidence": "EXTRACTED", "source_file": "lib/store/dev-actions.ts", "source_location": "L17", "weight": 1.0}, {"source": "dev_actions", "target": "avatarshowcasescenes", "relation": "imports_from", "confidence": "EXTRACTED", "source_file": "lib/store/dev-actions.ts", "source_location": "L18", "weight": 1.0}, {"source": "dev_actions", "target": "talkingheadlipsynctestscene", "relation": "imports_from", "confidence": "EXTRACTED", "source_file": "lib/store/dev-actions.ts", "source_location": "L19", "weight": 1.0}, {"source": "dev_actions", "target": "reactshowcasescenes", "relation": "imports_from", "confidence": "EXTRACTED", "source_file": "lib/store/dev-actions.ts", "source_location": "L20", "weight": 1.0}, {"source": "dev_actions", "target": "types", "relation": "imports_from", "confidence": "EXTRACTED", "source_file": "lib/store/dev-actions.ts", "source_location": "L21", "weight": 1.0}, {"source": "dev_actions", "target": "dev_actions_createdevactions", "relation": "contains", "confidence": "EXTRACTED", "source_file": "lib/store/dev-actions.ts", "source_location": "L23", "weight": 1.0}]}