{"nodes": [{"id": "templates", "label": "templates.ts", "file_type": "code", "source_file": "lib/db/seeds/templates.ts", "source_location": "L1"}, {"id": "templates_seedtemplates", "label": "seedTemplates()", "file_type": "code", "source_file": "lib/db/seeds/templates.ts", "source_location": "L5"}], "edges": [{"source": "templates", "target": "index", "relation": "imports_from", "confidence": "EXTRACTED", "source_file": "lib/db/seeds/templates.ts", "source_location": "L1", "weight": 1.0}, {"source": "templates", "target": "schema", "relation": "imports_from", "confidence": "EXTRACTED", "source_file": "lib/db/seeds/templates.ts", "source_location": "L2", "weight": 1.0}, {"source": "templates", "target": "drizzle_orm", "relation": "imports_from", "confidence": "EXTRACTED", "source_file": "lib/db/seeds/templates.ts", "source_location": "L3", "weight": 1.0}, {"source": "templates", "target": "templates_seedtemplates", "relation": "contains", "confidence": "EXTRACTED", "source_file": "lib/db/seeds/templates.ts", "source_location": "L5", "weight": 1.0}]}